easy_lightning/__init__.py
easy_lightning/cli.py
easy_lightning/cfg/config.yaml
easy_lightning/cfg/config2.yaml
easy_lightning/cfg/config_nn.yaml
easy_lightning/cfg/local_config.yaml
easy_lightning/cfg/torchvision_config.yaml
easy_lightning/cfg/app1/app1_2_file.yaml
easy_lightning/cfg/app2/app2_file.yaml
easy_lightning/cfg/app2/app2bis_file.yaml
easy_lightning/cfg/app3/app3_name.yaml
easy_lightning/cfg/model/nn.yaml
easy_lightning/cfg/model/resnet.yaml
easy_lightning/cfg/model/loader_params/loader_params_cfg.yaml
easy_lightning/cfg/model/trainer_params/trainer_params_cfg.yaml
easy_lightning/easy_data/__init__.py
easy_lightning/easy_data/_version.py
easy_lightning/easy_data/data.py
easy_lightning/easy_data/file.py
easy_lightning/easy_data/stat.py
easy_lightning/easy_data/stats.py
easy_lightning/easy_data/torch.py
easy_lightning/easy_data/transform.py
easy_lightning/easy_data/uci.py
easy_lightning/easy_data/utils.py
easy_lightning/easy_exp/__init__.py
easy_lightning/easy_exp/_version.py
easy_lightning/easy_exp/cfg.py
easy_lightning/easy_exp/exp.py
easy_lightning/easy_exp/plot_utils.py
easy_lightning/easy_exp/var.py
easy_lightning/easy_exp/wandb.py
easy_lightning/easy_rec/__init__.py
easy_lightning/easy_rec/_version.py
easy_lightning/easy_rec/callbacks.py
easy_lightning/easy_rec/data_generation_utils.py
easy_lightning/easy_rec/losses.py
easy_lightning/easy_rec/metrics.py
easy_lightning/easy_rec/preparation.py
easy_lightning/easy_rec/rec_torch.py
easy_lightning/easy_rec/remove_elements.py
easy_lightning/easy_rec/model/__init__.py
easy_lightning/easy_rec/model/_version.py
easy_lightning/easy_rec/model/graph/HSGCN.py
easy_lightning/easy_rec/model/graph/LightGCN.py
easy_lightning/easy_rec/model/graph/NGCF.py
easy_lightning/easy_rec/model/graph/__init__.py
easy_lightning/easy_rec/model/graph/sheaf.py
easy_lightning/easy_rec/model/graph/ultraGCN.py
easy_lightning/easy_rec/model/sequential/BERT4Rec.py
easy_lightning/easy_rec/model/sequential/CORE.py
easylightning-1.0.6.dist-info/LICENSE
easylightning-1.0.6.dist-info/METADATA
easylightning-1.0.6.dist-info/WHEEL
easylightning-1.0.6.dist-info/entry_points.txt
easylightning-1.0.6.dist-info/top_level.txt
easylightning-1.0.6.dist-info/RECORD
